README.md
davt_dependencies_python/__init__.py
pyproject.toml
setup.cfg
davt_dependencies_python-202304.0.7.dist-info/METADATA
davt_dependencies_python-202304.0.7.dist-info/WHEEL
davt_dependencies_python-202304.0.7.dist-info/RECORD
