Metadata-Version: 2.1
Name: davt-dependencies-python
Version: 202304.0.7
Summary: Data, Analytics and Visualization Templates (DAVT) - Python Dependencies
Home-page: https://github.com/cdcent/davt
License: Apache
Author: John Bowyer
Author-email: zfi4@cdc.gov
Requires-Python: >=3.9,<4.0
Classifier: Development Status :: 4 - Beta
Classifier: Environment :: Console
Classifier: Intended Audience :: Developers
Classifier: License :: Other/Proprietary License
Classifier: Operating System :: OS Independent
Classifier: Programming Language :: Python
Classifier: Programming Language :: Python :: 3
Classifier: Programming Language :: Python :: 3.9
Classifier: Programming Language :: Python :: 3.10
Classifier: Programming Language :: Python :: 3.11
Classifier: Programming Language :: Python :: 3.9
Requires-Dist: Sphinx (>=5.2.1,<6.0.0)
Requires-Dist: adal (>=1.2.7,<2.0.0)
Requires-Dist: azure-common (>=1.1.28,<2.0.0)
Requires-Dist: azure-identity (>=1.10.0,<2.0.0)
Requires-Dist: azure-keyvault (>=4.2.0,<5.0.0)
Requires-Dist: azure-keyvault-secrets (>=4.5.0,<5.0.0)
Requires-Dist: azure-storage-file-datalake (>=12.8.0,<13.0.0)
Requires-Dist: boto3 (==1.21.18)
Requires-Dist: botocore (==1.24.18)
Requires-Dist: chardet (>=5.0.0,<6.0.0)
Requires-Dist: docutils (==0.17.1)
Requires-Dist: markdown (>=3.4.1,<4.0.0)
Requires-Dist: myst-parser (>=0.18.0,<0.19.0)
Requires-Dist: nbconvert (>=6.5.1,<7.0.0)
Requires-Dist: numpy (>=1.23.0,<2.0.0)
Requires-Dist: opencensus (>=0.11.0,<0.12.0)
Requires-Dist: opencensus-ext-azure (>=1.1.7,<2.0.0)
Requires-Dist: openpyxl (>=3.0.4,<4.0.0)
Requires-Dist: pathlib (>=1.0.1,<2.0.0)
Requires-Dist: pip-system-certs (>=4.0,<5.0)
Requires-Dist: pyarrow (>=10.0.1,<11.0.0)
Requires-Dist: pygments (>=2.13.0,<3.0.0)
Requires-Dist: pyreadstat (>=1.1.9,<2.0.0)
Requires-Dist: pytest (>=7.1.2,<8.0.0)
Requires-Dist: pytest-cov (>=4.0.0,<5.0.0)
Requires-Dist: python-dateutil (>=2.8.2,<3.0.0)
Requires-Dist: python-dotenv (>=0.20.0,<0.21.0)
Requires-Dist: requests (>=2.28.1,<3.0.0)
Requires-Dist: rsconnect-jupyter (>=1.6.0,<2.0.0)
Requires-Dist: setuptools (==65.6.3)
Requires-Dist: sphinx-autoapi (>=2.0.0,<3.0.0)
Requires-Dist: sphinx-autodoc-typehints (>=1.19.5,<2.0.0)
Requires-Dist: sphinx-markdown-builder (>=0.5.5,<0.6.0)
Requires-Dist: sphinx-markdown-tables (>=0.0.17,<0.0.18)
Requires-Dist: sphinx-rtd-theme (>=1.1.1,<2.0.0)
Requires-Dist: sphinx-sitemap (>=2.2.0,<3.0.0)
Requires-Dist: sphinx-sql (>=1.3.2,<2.0.0)
Requires-Dist: sphinxcontrib-mermaid (>=0.7.1,<0.8.0)
Requires-Dist: style (>=1.1.6,<2.0.0)
Requires-Dist: testresources (>=2.0.1,<3.0.0)
Project-URL: Repository, https://github.com/cdcent/davt
